{
  "$id": "https://datastream.org/schema/data/quality-control/ResultUnit-Turbidity.json",
  "title": "ResultUnit-Turbidity",
  "description": "",
  "errorMessage": "qc-ResultUnit-Turbidity",
  "if": {
    "type": "object",
    "unevaluatedProperties": true,
    "properties": {
      "ResultUnit": {
        "enum": ["FNU", "FTU", "JTU", "NTU"]
      }
    },
    "required": ["ResultUnit"]
  },
  "then": {
    "type": "object",
    "unevaluatedProperties": true,
    "properties": {
      "CharacteristicName": {
        "enum": ["Turbidity"]
      }
    },
    "required": ["CharacteristicName"]
  }
}
